{
  "required": true,
  "package": "net.pixeldreamstudios.morequesttypes.mixin",
  "compatibilityLevel": "JAVA_21",
  "mixins": [
    "LivingEntityLastDamageMixin",
    "QuestExtensions",
    "RewardExtensions",
    "TaskExtensions",
    "TaskExtensionsOrigins",
    "TeamDataOriginMixin",
    "ItemTaskSubmitMixin",
    "AbstractBooleanTaskExtensionMixin",
    "TaskExtensionsPlayerLeveling",
    "TeamDataPlayerLevelingMixin",
    "MerchantResultSlotMixin",
    "accessor.SkillsClientModAccessor",
    "accessor.ClientSkillScreenDataAccessor",
    "accessor.MobAccessor",
    "QuestSummonedEntityMixin"

  ],
  "injectors": {
    "defaultRequire": 0
  }
}